btsocket/__init__.py
btsocket/btmgmt_callback.py
btsocket/btmgmt_protocol.py
btsocket/btmgmt_socket.py
btsocket/btmgmt_sync.py
btsocket/tools.py
btsocket-0.3.0.dist-info/LICENSE
btsocket-0.3.0.dist-info/METADATA
btsocket-0.3.0.dist-info/WHEEL
btsocket-0.3.0.dist-info/top_level.txt
btsocket-0.3.0.dist-info/RECORD
