Metadata-Version: 2.1
Name: btsocket
Version: 0.3.0
Summary: Python library for BlueZ Bluetooth Management API
Home-page: https://github.com/ukBaz/python-btsocket
Author: Barry Byford
Author-email: barry_byford@yahoo.co.uk
Maintainer: Barry Byford
Maintainer-email: barry_byford@yahoo.co.uk
License: MIT
Keywords: BlueZ Bluetooth Management MGMT API
Classifier: Development Status :: 3 - Alpha
Classifier: Intended Audience :: Developers
Classifier: Intended Audience :: Education
Classifier: Topic :: System :: Hardware
Classifier: Topic :: Software Development :: Embedded Systems
Classifier: Topic :: Home Automation
Classifier: Topic :: Education
Classifier: License :: OSI Approved :: MIT License
Classifier: Programming Language :: Python :: 3 :: Only
License-File: LICENSE
Provides-Extra: rel
Requires-Dist: bumpversion; extra == "rel"
Requires-Dist: twine; extra == "rel"
Provides-Extra: docs
Requires-Dist: sphinx; extra == "docs"
Requires-Dist: sphinx_rtd_theme; extra == "docs"
Requires-Dist: pygments; extra == "docs"
Provides-Extra: test
Requires-Dist: coverage; extra == "test"
Requires-Dist: pycodestyle; extra == "test"
Provides-Extra: dev
Requires-Dist: bumpversion; extra == "dev"
Requires-Dist: twine; extra == "dev"
Requires-Dist: sphinx; extra == "dev"
Requires-Dist: sphinx_rtd_theme; extra == "dev"
Requires-Dist: pygments; extra == "dev"
Requires-Dist: coverage; extra == "dev"
Requires-Dist: pycodestyle; extra == "dev"
